durguestprofile/__init__.py
durguestprofile/ftps.py
durguestprofile/functions.py
durguestprofile/guest_profile.py
durguestprofile/utilities.py
durguestprofile/xmltodict.py
durguestprofile/support/__init__.py
durguestprofile-2.0.2.dist-info/LICENSE
durguestprofile-2.0.2.dist-info/METADATA
durguestprofile-2.0.2.dist-info/WHEEL
durguestprofile-2.0.2.dist-info/top_level.txt
durguestprofile-2.0.2.dist-info/RECORD
