Metadata-Version: 2.1
Name: durguestprofile
Version: 2.0.2
Summary: Dur Guest Data Accuracy Measurement Tool
Home-page: 
Author: ROInsight.com - Muhammad Khlef
Author-email: <support@roinsight.com>
License: BSD
Keywords: python,dur,guest,opera,profile,audit
Classifier: Development Status :: 5 - Production/Stable
Classifier: Programming Language :: Python
Classifier: Programming Language :: Python :: 3
Classifier: License :: OSI Approved :: BSD License
Classifier: Operating System :: OS Independent
Classifier: Topic :: Software Development :: Interpreters
Classifier: Topic :: Software Development :: Version Control :: Git
License-File: LICENSE
Requires-Dist: numpy (>=1.23.5)
Requires-Dist: pandas (>=1.5.3)
Requires-Dist: XlsxWriter (>=3.0.3)
Requires-Dist: lxml (>=4.9.1)
Requires-Dist: pyparsing (>=3.0.9)
Requires-Dist: openpyxl (>=3.0.10)
Requires-Dist: customtkinter (==5.1.2)
Requires-Dist: sparse-dot-topn (>=0.3.1)
Requires-Dist: scikit-learn (>=1.1.1)
Requires-Dist: scipy (>=1.10.0)
Requires-Dist: matplotlib (==3.7.1)
Requires-Dist: google-i18n-address (==2.5.2)
Requires-Dist: phonenumbers (==8.13.8)
Requires-Dist: pysftp (==0.2.9)
